Workbook

Sheet Assumptions
B2: CORTEX — Financial & Pricing Model
B3: Business Intelligence Operating System (BIOS) · v1.0 · June 2026
B4: SEA/Malaysia-anchored pricing · EU & Premium variants · recurring figures standardised to USD
B6: KEY ASSUMPTIONS (blue = editable inputs)
B7: Assumption | C7: Value | D7: Note
B8: FX: USD per MYR | C8: 0.213 | D8: 1 USD ~ 4.70 MYR (Jun 2026)
B9: FX: USD per EUR | C9: 1.07 | D9: 1 EUR ~ 0.935 USD
B10: Blended implementation labour cost / hr (USD) | C10: 42 | D10: Internal: Karim + KL contractors, Yr1-2
B11: Subscription COGS - Starter / mo (USD) | C11: 25 | D11: Shared multi-tenant hosting + LLM tokens
B12: Subscription COGS - Growth / mo (USD) | C12: 90 | D12: Multi-tenant, more docs + integrations
B13: Subscription COGS - Professional / mo (USD) | C13: 350 | D13: Multi/isolated tenant, heavier compute
B14: Subscription COGS - Enterprise / mo (USD) | C14: 1400 | D14: Single-tenant / VPC, heavy LLM + governance
B15: Gross logo retention (annual) | C15: 0.85 | D15: Active-base roll-forward
B16: Net revenue retention (expansion) | C16: 1.15 | D16: Land-and-expand up the maturity ladder
B18: TABS
B19: Offer Structure | C19: -> | D19: 4-tier ladder: features, limits, AI, automations, support
B20: Pricing - SEA | C20: -> | D20: Malaysia / SEA price book (MYR), anchor market
B21: Pricing - EU | C21: -> | D21: Europe / DACH price book (EUR)
B22: Pricing - Premium | C22: -> | D22: Global Premium Enterprise price book (USD)
B23: Margin Analysis | C23: -> | D23: Per-tier subscription & implementation margins
B24: Revenue Model | C24: -> | D24: 3-year bookings, ARR, P&L, EBITDA
B25: Headcount | C25: -> | D25: Hiring plan vs. revenue per phase

Sheet Offer Structure
A2: The CORTEX Product Ladder - 4 Tiers
A3: One platform, five maturity levels, four company sizes. Customers climb - never re-platform.
B5: STARTER | C5: GROWTH | D5: PROFESSIONAL | E5: ENTERPRISE
A6: Target customer | B6: Solo / micro (1-10) | C6: SME (10-250) | D6: Mid-market (250-2,500) | E6: Enterprise (2,500-10,000+)
A7: Maturity journey | B7: Level 1 -> 2 | C7: Level 2 -> 3 | D7: Level 3 -> 4 | E7: Level 4 -> 5
A8: Outcome | B8: Find & trust answers | C8: Brain runs the work | D8: Brain helps decide | E8: Business runs on it
A9: Brain layers active | B9: 2-3 (Knowledge, Ops +1) | C9: 4-5 | D9: 6-7 | E9: All 8 lobes
A10: Documents ingested | B10: Up to 500 | C10: Up to 5,000 | D10: Up to 50,000 | E10: Unlimited
A11: Data sources | B11: 3 (uploaded) | C11: 8 (docs + first APIs) | D11: 15+ live integrations | E11: Unlimited + custom connectors
A12: AI functions | B12: Grounded Q&A, source citation, confidence bands | C12: + On-brand content, ops drafting, task running | D12: + Decision scoring engine, agents, scenarios | E12: + Custom scoring models, multi-brain, full agents
A13: Automations | B13: Read-only briefs only | C13: Basic schedules & reminders | D13: Workflows + tool integrations | E13: Full autonomous cadence + custom triggers
A14: Dashboard | B14: Search + ask box | C14: + Knowledge-graph view, briefs | D14: + Scorecards, reports, graph analytics | E14: + Role-aware enterprise dashboards
A15: Governance / RBAC | B15: Owner / flat | C15: A few roles | D15: Department clearances | E15: Fine-grained, SSO, full audit trail
A16: Deployment | B16: Shared multi-tenant | C16: Multi-tenant | D16: Multi-tenant or isolated | E16: Single-tenant / VPC / on-prem
A17: Trust & verification | B17: Sourcing + no-fabrication | C17: + Human-approval tiers | D17: + Adversarial self-check | E17: + Premium governance & compliance pack
A18: Support | B18: Self-serve + docs | C18: Light onboarding | D18: Guided implementation | E18: Dedicated success manager + SLA

Sheet Pricing - SEA
A2: Pricing - Malaysia / Southeast Asia (MYR) · ANCHOR MARKET
A3: Anchored to KL/SEA willingness-to-pay. Enterprise = annual contract; figures are floors.
B5: STARTER | C5: GROWTH | D5: PROFESSIONAL | E5: ENTERPRISE
A6: One-time setup (CORTEX Method) | B6: 6000 | C6: 18000 | D6: 45000 | E6: 120000
A7: Monthly platform fee | B7: 1200 | C7: 3500 | D7: 8000 | E7: 18000
A8: Annual platform value (12 mo) | B8: =B7*12 -> 14400 | C8: =C7*12 -> 42000 | D8: =D7*12 -> 96000 | E8: =E7*12 -> 216000
A9: Year-1 total (setup + 12 mo) | B9: =B6+B8 -> 20400 | C9: =C6+C8 -> 60000 | D9: =D6+D8 -> 141000 | E9: =E6+E8 -> 336000
A11: ADD-ONS (monetise the variable layer)
A12: Add-on | B12: Price
A13: Extra industry template | B13: RM 4,000
A14: Additional brand-brain (agencies) | B14: RM 1,500/mo
A15: Premium integration (per system) | B15: RM 800/mo
A16: On-site capture workshop (1 day) | B16: RM 3,500
A17: Compliance pack (PDPA / industry) | B17: RM 6,000

Sheet Pricing - EU
A2: Pricing - Europe / DACH (EUR)
A3: Higher willingness-to-pay; GDPR governance is a premium selling point, not a cost.
B5: STARTER | C5: GROWTH | D5: PROFESSIONAL | E5: ENTERPRISE
A6: One-time setup (CORTEX Method) | B6: 2500 | C6: 8000 | D6: 22000 | E6: 65000
A7: Monthly platform fee | B7: 450 | C7: 1400 | D7: 3500 | E7: 8500
A8: Annual platform value (12 mo) | B8: =B7*12 -> 5400 | C8: =C7*12 -> 16800 | D8: =D7*12 -> 42000 | E8: =E7*12 -> 102000
A9: Year-1 total (setup + 12 mo) | B9: =B6+B8 -> 7900 | C9: =C6+C8 -> 24800 | D9: =D6+D8 -> 64000 | E9: =E6+E8 -> 167000
A11: ADD-ONS (monetise the variable layer)
A12: Add-on | B12: Price
A13: Extra industry template | B13: EUR 1,500
A14: Additional brand-brain (agencies) | B14: EUR 500/mo
A15: Premium integration (per system) | B15: EUR 250/mo
A16: On-site capture workshop (1 day) | B16: EUR 1,800
A17: Compliance pack (GDPR / industry) | B17: EUR 2,500

Sheet Pricing - Premium
A2: Pricing - Global Premium Enterprise (USD) · single-tenant / VPC
A3: For regulated & large global buyers needing isolation, custom templates, dedicated success.
B5: STARTER | C5: GROWTH | D5: PROFESSIONAL | E5: ENTERPRISE
A6: One-time setup (CORTEX Method) | B6: 3000 | C6: 12000 | D6: 35000 | E6: 90000
A7: Monthly platform fee | B7: 600 | C7: 2000 | D7: 6000 | E7: 15000
A8: Annual platform value (12 mo) | B8: =B7*12 -> 7200 | C8: =C7*12 -> 24000 | D8: =D7*12 -> 72000 | E8: =E7*12 -> 180000
A9: Year-1 total (setup + 12 mo) | B9: =B6+B8 -> 10200 | C9: =C6+C8 -> 36000 | D9: =D6+D8 -> 107000 | E9: =E6+E8 -> 270000
A11: ADD-ONS (monetise the variable layer)
A12: Add-on | B12: Price
A13: Extra industry template | B13: $ 5,000
A14: Additional brand-brain | B14: $ 1,000/mo
A15: Premium integration (per system) | B15: $ 500/mo
A16: Dedicated success manager | B16: $ 3,000/mo
A17: On-prem / VPC deployment | B17: from $ 25,000

Sheet Margin Analysis
A2: Margin Analysis (per tier, USD)
A3: SEA prices converted to USD at the FX input. Subscription = high-margin SaaS; implementation = lower-margin services that fund the build and lock in the platform.
B5: STARTER | C5: GROWTH | D5: PROFESSIONAL | E5: ENTERPRISE
A6: Monthly fee (USD) | B6: =1200*Assumptions!$C$8 -> 255.6 | C6: =3500*Assumptions!$C$8 -> 745.5 | D6: =8000*Assumptions!$C$8 -> 1704 | E6: =18000*Assumptions!$C$8 -> 3834
A7: Monthly subscription COGS (USD) | B7: =Assumptions!$C$11 -> 25 | C7: =Assumptions!$C$12 -> 90 | D7: =Assumptions!$C$13 -> 350 | E7: =Assumptions!$C$14 -> 1400
A8: Monthly gross profit (USD) | B8: =B6-B7 -> 230.6 | C8: =C6-C7 -> 655.5 | D8: =D6-D7 -> 1354 | E8: =E6-E7 -> 2434
A9: Subscription gross margin % | B9: =B8/B6 -> 0.90219092 | C9: =C8/C6 -> 0.87927565 | D9: =D8/D6 -> 0.79460094 | E9: =E8/E6 -> 0.63484611
A11: Setup price (USD) | B11: =6000*Assumptions!$C$8 -> 1278 | C11: =18000*Assumptions!$C$8 -> 3834 | D11: =45000*Assumptions!$C$8 -> 9585 | E11: =120000*Assumptions!$C$8 -> 25560
A12: Implementation labour hours | B12: 16 | C12: 50 | D12: 130 | E12: 320
A13: Implementation cost (USD) | B13: =B12*Assumptions!$C$10 -> 672 | C13: =C12*Assumptions!$C$10 -> 2100 | D13: =D12*Assumptions!$C$10 -> 5460 | E13: =E12*Assumptions!$C$10 -> 13440
A14: Implementation gross profit (USD) | B14: =B11-B13 -> 606 | C14: =C11-C13 -> 1734 | D14: =D11-D13 -> 4125 | E14: =E11-E13 -> 12120
A15: Implementation gross margin % | B15: =B14/B11 -> 0.4741784 | C15: =C14/C11 -> 0.45226917 | D15: =D14/D11 -> 0.43035994 | E15: =E14/E11 -> 0.4741784
A17: Year-1 revenue (setup + 12mo, USD) | B17: =B11+B6*12 -> 4345.2 | C17: =C11+C6*12 -> 12780 | D17: =D11+D6*12 -> 30033 | E17: =E11+E6*12 -> 71568
A18: Year-1 COGS (impl + 12mo subs, USD) | B18: =B13+B7*12 -> 972 | C18: =C13+C7*12 -> 3180 | D18: =D13+D7*12 -> 9660 | E18: =E13+E7*12 -> 30240
A19: Year-1 blended gross margin % | B19: =(B17-B18)/B17 -> 0.77630489 | C19: =(C17-C18)/C17 -> 0.75117371 | D19: =(D17-D18)/D17 -> 0.67835381 | E19: =(E17-E18)/E17 -> 0.57746479
A21: Scalability: as templates mature and self-serve onboarding replaces hands-on capture, implementation hours fall and subscription mix rises - blended margin trends toward 80%+.

Sheet Revenue Model
A2: 3-Year Revenue Model (USD) - Base Case
A3: Phase 1 services-led pilots -> Phase 2 productised platform -> Phase 3 platform-led growth. Active base rolls forward at 85% logo retention.
B5: Year 1 (2026-27) | C5: Year 2 (2027-28) | D5: Year 3 (2028-29)
A6: NEW LOGOS
A7: Starter | B7: 5 | C7: 30 | D7: 110
A8: Growth | B8: 8 | C8: 22 | D8: 45
A9: Professional | B9: 3 | C9: 8 | D9: 18
A10: Enterprise | B10: 0 | C10: 2 | D10: 6
A11: Total new logos | B11: =SUM(B7:B10) -> 16 | C11: =SUM(C7:C10) -> 62 | D11: =SUM(D7:D10) -> 179
A13: ACTIVE BASE (end of year)
A14: Starter | B14: =B7 -> 5 | C14: =B14*Assumptions!$C$15+C7 -> 34.25 | D14: =C14*Assumptions!$C$15+D7 -> 139.1125
A15: Growth | B15: =B8 -> 8 | C15: =B15*Assumptions!$C$15+C8 -> 28.8 | D15: =C15*Assumptions!$C$15+D8 -> 69.48
A16: Professional | B16: =B9 -> 3 | C16: =B16*Assumptions!$C$15+C9 -> 10.55 | D16: =C16*Assumptions!$C$15+D9 -> 26.9675
A17: Enterprise | B17: =B10 -> 0 | C17: =B17*Assumptions!$C$15+C10 -> 2 | D17: =C17*Assumptions!$C$15+D10 -> 7.7
A18: Total active clients | B18: =SUM(B14:B17) -> 16 | C18: =SUM(C14:C17) -> 75.6 | D18: =SUM(D14:D17) -> 243.26
A20: REVENUE (USD)
A21: Setup / implementation revenue | B21: =B7*1278+B8*3834+B9*9585+B10*25560 -> 65817 | C21: =C7*1278+C8*3834+C9*9585+C10*25560 -> 250488 | D21: =D7*1278+D8*3834+D9*9585+D10*25560 -> 639000
A22: Recurring revenue (from active base) | B22: =B14*3067+B15*8946+B16*20448+B17*46008 -> 148247 | C22: =C14*3067+C15*8946+C16*20448+C17*46008 -> 670431.95 | D22: =D14*3067+D15*8946+D16*20448+D17*46008 -> 1953919.2
A23: Total revenue | B23: =B21+B22 -> 214064 | C23: =C21+C22 -> 920919.95 | D23: =D21+D22 -> 2592919.2
A25: COST & PROFIT (USD)
A26: COGS (impl labour + hosting/LLM) | B26: =B21*0.45+B22*0.2 -> 59267.05 | C26: =C21*0.45+C22*0.2 -> 246805.99 | D26: =D21*0.45+D22*0.2 -> 678333.83
A27: Gross profit | B27: =B23-B26 -> 154796.95 | C27: =C23-C26 -> 674113.96 | D27: =D23-D26 -> 1914585.3
A28: Gross margin % | B28: =B27/B23 -> 0.72313397 | C28: =C27/C23 -> 0.7320006 | D28: =D27/D23 -> 0.7383899
A30: Operating expenses (team, S&M, G&A) | B30: 180000 | C30: 520000 | D30: 1150000
A31: EBITDA | B31: =B27-B30 -> -25203.05 | C31: =C27-C30 -> 154113.96 | D31: =D27-D30 -> 764585.33
A32: EBITDA margin % | B32: =B31/B23 -> -0.11773605 | C32: =C31/C23 -> 0.16734784 | D32: =D31/D23 -> 0.29487434
A34: Exit-rate MRR (recurring / 12) | B34: =B22/12 -> 12353.917 | C34: =C22/12 -> 55869.329 | D34: =D22/12 -> 162826.6

Sheet Headcount
A2: Headcount Plan
A3: Lean services-led start; hire ahead of platform and template scale. FTEs + contractors.
A5: Role | B5: Year 1 | C5: Year 2 | D5: Year 3
A6: Founder / lead (Karim) | B6: 1 | C6: 1 | D6: 1
A7: AI / full-stack engineers | B7: 1 | C7: 3 | D7: 6
A8: Implementation consultants | B8: 1 | C8: 3 | D8: 7
A9: Sales / partnerships | B9: 0 | C9: 2 | D9: 5
A10: Customer success | B10: 0 | C10: 1 | D10: 4
A11: Marketing / content | B11: 1 | C11: 1 | D11: 3
A12: Ops / admin / finance | B12: 0 | C12: 1 | D12: 2
A13: Total headcount | B13: =SUM(B6:B12) -> 4 | C13: =SUM(C6:C12) -> 12 | D13: =SUM(D6:D12) -> 28
A15: Revenue per head (USD) | B15: ='Revenue Model'!B23/B13 -> 53516 | C15: ='Revenue Model'!C23/C13 -> 76743.329 | D15: ='Revenue Model'!D23/D13 -> 92604.256
